[
  {
    "endIndex": 1,
    "sectionBreak": {
      "sectionStyle": {
        "columnSeparatorStyle": "NONE",
        "contentDirection": "LEFT_TO_RIGHT",
        "sectionType": "CONTINUOUS"
      }
    }
  },
  {
    "startIndex": 1,
    "endIndex": 20,
    "paragraph": {
      "elements": [
        {
          "startIndex": 1,
          "endIndex": 6,
          "textRun": {
            "content": "Test ",
            "textStyle": {}
          }
        },
        {
          "startIndex": 6,
          "endIndex": 16,
          "textRun": {
            "content": "paragraph ",
            "textStyle": {
              "bold": true
            }
          }
        },
        {
          "startIndex": 16,
          "endIndex": 20,
          "textRun": {
            "content": "yep\n",
            "textStyle": {}
          }
        }
      ],
      "paragraphStyle": {
        "namedStyleType": "NORMAL_TEXT",
        "direction": "LEFT_TO_RIGHT"
      }
    }
  },
  {
    "startIndex": 20,
    "endIndex": 21,
    "paragraph": {
      "elements": [
        {
          "startIndex": 20,
          "endIndex": 21,
          "textRun": {
            "content": "\n",
            "textStyle": {}
          }
        }
      ],
      "paragraphStyle": {
        "namedStyleType": "NORMAL_TEXT",
        "direction": "LEFT_TO_RIGHT"
      }
    }
  },
  {
    "startIndex": 21,
    "endIndex": 77,
    "table": {
      "rows": 2,
      "columns": 2,
      "tableRows": [
        {
          "startIndex": 22,
          "endIndex": 71,
          "tableCells": [
            {
              "startIndex": 23,
              "endIndex": 27,
              "content": [
                {
                  "startIndex": 24,
                  "endIndex": 27,
                  "paragraph": {
                    "elements": [
                      {
                        "startIndex": 24,
                        "endIndex": 27,
                        "textRun": {
                          "content": "hi\n",
                          "textStyle": {}
                        }
                      }
                    ],
                    "paragraphStyle": {
                      "namedStyleType": "NORMAL_TEXT",
                      "alignment": "START",
                      "lineSpacing": 100,
                      "direction": "LEFT_TO_RIGHT",
                      "spacingMode": "COLLAPSE_LISTS",
                      "spaceAbove": {
                        "unit": "PT"
                      },
                      "spaceBelow": {
                        "unit": "PT"
                      },
                      "borderBetween": {
                        "color": {},
                        "width": {
                          "unit": "PT"
                        },
                        "padding": {
                          "unit": "PT"
                        },
                        "dashStyle": "SOLID"
                      },
                      "borderTop": {
                        "color": {},
                        "width": {
                          "unit": "PT"
                        },
                        "padding": {
                          "unit": "PT"
                        },
                        "dashStyle": "SOLID"
                      },
                      "borderBottom": {
                        "color": {},
                        "width": {
                          "unit": "PT"
                        },
                        "padding": {
                          "unit": "PT"
                        },
                        "dashStyle": "SOLID"
                      },
                      "borderLeft": {
                        "color": {},
                        "width": {
                          "unit": "PT"
                        },
                        "padding": {
                          "unit": "PT"
                        },
                        "dashStyle": "SOLID"
                      },
                      "borderRight": {
                        "color": {},
                        "width": {
                          "unit": "PT"
                        },
                        "padding": {
                          "unit": "PT"
                        },
                        "dashStyle": "SOLID"
                      },
                      "indentFirstLine": {
                        "unit": "PT"
                      },
                      "indentStart": {
                        "unit": "PT"
                      },
                      "indentEnd": {
                        "unit": "PT"
                      },
                      "keepLinesTogether": false,
                      "keepWithNext": false,
                      "avoidWidowAndOrphan": false,
                      "shading": {
                        "backgroundColor": {}
                      }
                    }
                  }
                }
              ],
              "tableCellStyle": {
                "rowSpan": 1,
                "columnSpan": 1,
                "backgroundColor": {},
                "paddingLeft": {
                  "magnitude": 5,
                  "unit": "PT"
                },
                "paddingRight": {
                  "magnitude": 5,
                  "unit": "PT"
                },
                "paddingTop": {
                  "magnitude": 5,
                  "unit": "PT"
                },
                "paddingBottom": {
                  "magnitude": 5,
                  "unit": "PT"
                },
                "contentAlignment": "TOP"
              }
            },
            {
              "startIndex": 27,
              "endIndex": 71,
              "content": [
                {
                  "startIndex": 28,
                  "endIndex": 35,
                  "paragraph": {
                    "elements": [
                      {
                        "startIndex": 28,
                        "endIndex": 35,
                        "textRun": {
                          "content": "inside\n",
                          "textStyle": {}
                        }
                      }
                    ],
                    "paragraphStyle": {
                      "namedStyleType": "NORMAL_TEXT",
                      "alignment": "START",
                      "lineSpacing": 100,
                      "direction": "LEFT_TO_RIGHT",
                      "spacingMode": "COLLAPSE_LISTS",
                      "spaceAbove": {
                        "unit": "PT"
                      },
                      "spaceBelow": {
                        "unit": "PT"
                      },
                      "borderBetween": {
                        "color": {},
                        "width": {
                          "unit": "PT"
                        },
                        "padding": {
                          "unit": "PT"
                        },
                        "dashStyle": "SOLID"
                      },
                      "borderTop": {
                        "color": {},
                        "width": {
                          "unit": "PT"
                        },
                        "padding": {
                          "unit": "PT"
                        },
                        "dashStyle": "SOLID"
                      },
                      "borderBottom": {
                        "color": {},
                        "width": {
                          "unit": "PT"
                        },
                        "padding": {
                          "unit": "PT"
                        },
                        "dashStyle": "SOLID"
                      },
                      "borderLeft": {
                        "color": {},
                        "width": {
                          "unit": "PT"
                        },
                        "padding": {
                          "unit": "PT"
                        },
                        "dashStyle": "SOLID"
                      },
                      "borderRight": {
                        "color": {},
                        "width": {
                          "unit": "PT"
                        },
                        "padding": {
                          "unit": "PT"
                        },
                        "dashStyle": "SOLID"
                      },
                      "indentFirstLine": {
                        "unit": "PT"
                      },
                      "indentStart": {
                        "unit": "PT"
                      },
                      "indentEnd": {
                        "unit": "PT"
                      },
                      "keepLinesTogether": false,
                      "keepWithNext": false,
                      "avoidWidowAndOrphan": false,
                      "shading": {
                        "backgroundColor": {}
                      }
                    }
                  }
                },
                {
                  "startIndex": 35,
                  "endIndex": 36,
                  "paragraph": {
                    "elements": [
                      {
                        "startIndex": 35,
                        "endIndex": 36,
                        "textRun": {
                          "content": "\n",
                          "textStyle": {}
                        }
                      }
                    ],
                    "paragraphStyle": {
                      "namedStyleType": "NORMAL_TEXT",
                      "alignment": "START",
                      "lineSpacing": 100,
                      "direction": "LEFT_TO_RIGHT",
                      "spacingMode": "COLLAPSE_LISTS",
                      "spaceAbove": {
                        "unit": "PT"
                      },
                      "spaceBelow": {
                        "unit": "PT"
                      },
                      "borderBetween": {
                        "color": {},
                        "width": {
                          "unit": "PT"
                        },
                        "padding": {
                          "unit": "PT"
                        },
                        "dashStyle": "SOLID"
                      },
                      "borderTop": {
                        "color": {},
                        "width": {
                          "unit": "PT"
                        },
                        "padding": {
                          "unit": "PT"
                        },
                        "dashStyle": "SOLID"
                      },
                      "borderBottom": {
                        "color": {},
                        "width": {
                          "unit": "PT"
                        },
                        "padding": {
                          "unit": "PT"
                        },
                        "dashStyle": "SOLID"
                      },
                      "borderLeft": {
                        "color": {},
                        "width": {
                          "unit": "PT"
                        },
                        "padding": {
                          "unit": "PT"
                        },
                        "dashStyle": "SOLID"
                      },
                      "borderRight": {
                        "color": {},
                        "width": {
                          "unit": "PT"
                        },
                        "padding": {
                          "unit": "PT"
                        },
                        "dashStyle": "SOLID"
                      },
                      "indentFirstLine": {
                        "unit": "PT"
                      },
                      "indentStart": {
                        "unit": "PT"
                      },
                      "indentEnd": {
                        "unit": "PT"
                      },
                      "keepLinesTogether": false,
                      "keepWithNext": false,
                      "avoidWidowAndOrphan": false,
                      "shading": {
                        "backgroundColor": {}
                      }
                    }
                  }
                },
                {
                  "startIndex": 36,
                  "endIndex": 70,
                  "table": {
                    "rows": 2,
                    "columns": 1,
                    "tableRows": [
                      {
                        "startIndex": 37,
                        "endIndex": 53,
                        "tableCells": [
                          {
                            "startIndex": 38,
                            "endIndex": 53,
                            "content": [
                              {
                                "startIndex": 39,
                                "endIndex": 53,
                                "paragraph": {
                                  "elements": [
                                    {
                                      "startIndex": 39,
                                      "endIndex": 53,
                                      "textRun": {
                                        "content": "one point one\n",
                                        "textStyle": {}
                                      }
                                    }
                                  ],
                                  "paragraphStyle": {
                                    "namedStyleType": "NORMAL_TEXT",
                                    "alignment": "START",
                                    "lineSpacing": 100,
                                    "direction": "LEFT_TO_RIGHT",
                                    "spacingMode": "COLLAPSE_LISTS",
                                    "spaceAbove": {
                                      "unit": "PT"
                                    },
                                    "spaceBelow": {
                                      "unit": "PT"
                                    },
                                    "borderBetween": {
                                      "color": {},
                                      "width": {
                                        "unit": "PT"
                                      },
                                      "padding": {
                                        "unit": "PT"
                                      },
                                      "dashStyle": "SOLID"
                                    },
                                    "borderTop": {
                                      "color": {},
                                      "width": {
                                        "unit": "PT"
                                      },
                                      "padding": {
                                        "unit": "PT"
                                      },
                                      "dashStyle": "SOLID"
                                    },
                                    "borderBottom": {
                                      "color": {},
                                      "width": {
                                        "unit": "PT"
                                      },
                                      "padding": {
                                        "unit": "PT"
                                      },
                                      "dashStyle": "SOLID"
                                    },
                                    "borderLeft": {
                                      "color": {},
                                      "width": {
                                        "unit": "PT"
                                      },
                                      "padding": {
                                        "unit": "PT"
                                      },
                                      "dashStyle": "SOLID"
                                    },
                                    "borderRight": {
                                      "color": {},
                                      "width": {
                                        "unit": "PT"
                                      },
                                      "padding": {
                                        "unit": "PT"
                                      },
                                      "dashStyle": "SOLID"
                                    },
                                    "indentFirstLine": {
                                      "unit": "PT"
                                    },
                                    "indentStart": {
                                      "unit": "PT"
                                    },
                                    "indentEnd": {
                                      "unit": "PT"
                                    },
                                    "keepLinesTogether": false,
                                    "keepWithNext": false,
                                    "avoidWidowAndOrphan": false,
                                    "shading": {
                                      "backgroundColor": {}
                                    }
                                  }
                                }
                              }
                            ],
                            "tableCellStyle": {
                              "rowSpan": 1,
                              "columnSpan": 1,
                              "backgroundColor": {},
                              "paddingLeft": {
                                "magnitude": 5,
                                "unit": "PT"
                              },
                              "paddingRight": {
                                "magnitude": 5,
                                "unit": "PT"
                              },
                              "paddingTop": {
                                "magnitude": 5,
                                "unit": "PT"
                              },
                              "paddingBottom": {
                                "magnitude": 5,
                                "unit": "PT"
                              },
                              "contentAlignment": "TOP"
                            }
                          }
                        ],
                        "tableRowStyle": {
                          "minRowHeight": {
                            "unit": "PT"
                          }
                        }
                      },
                      {
                        "startIndex": 53,
                        "endIndex": 69,
                        "tableCells": [
                          {
                            "startIndex": 54,
                            "endIndex": 69,
                            "content": [
                              {
                                "startIndex": 55,
                                "endIndex": 69,
                                "paragraph": {
                                  "elements": [
                                    {
                                      "startIndex": 55,
                                      "endIndex": 69,
                                      "textRun": {
                                        "content": "one point two\n",
                                        "textStyle": {}
                                      }
                                    }
                                  ],
                                  "paragraphStyle": {
                                    "namedStyleType": "NORMAL_TEXT",
                                    "alignment": "START",
                                    "lineSpacing": 100,
                                    "direction": "LEFT_TO_RIGHT",
                                    "spacingMode": "COLLAPSE_LISTS",
                                    "spaceAbove": {
                                      "unit": "PT"
                                    },
                                    "spaceBelow": {
                                      "unit": "PT"
                                    },
                                    "borderBetween": {
                                      "color": {},
                                      "width": {
                                        "unit": "PT"
                                      },
                                      "padding": {
                                        "unit": "PT"
                                      },
                                      "dashStyle": "SOLID"
                                    },
                                    "borderTop": {
                                      "color": {},
                                      "width": {
                                        "unit": "PT"
                                      },
                                      "padding": {
                                        "unit": "PT"
                                      },
                                      "dashStyle": "SOLID"
                                    },
                                    "borderBottom": {
                                      "color": {},
                                      "width": {
                                        "unit": "PT"
                                      },
                                      "padding": {
                                        "unit": "PT"
                                      },
                                      "dashStyle": "SOLID"
                                    },
                                    "borderLeft": {
                                      "color": {},
                                      "width": {
                                        "unit": "PT"
                                      },
                                      "padding": {
                                        "unit": "PT"
                                      },
                                      "dashStyle": "SOLID"
                                    },
                                    "borderRight": {
                                      "color": {},
                                      "width": {
                                        "unit": "PT"
                                      },
                                      "padding": {
                                        "unit": "PT"
                                      },
                                      "dashStyle": "SOLID"
                                    },
                                    "indentFirstLine": {
                                      "unit": "PT"
                                    },
                                    "indentStart": {
                                      "unit": "PT"
                                    },
                                    "indentEnd": {
                                      "unit": "PT"
                                    },
                                    "keepLinesTogether": false,
                                    "keepWithNext": false,
                                    "avoidWidowAndOrphan": false,
                                    "shading": {
                                      "backgroundColor": {}
                                    }
                                  }
                                }
                              }
                            ],
                            "tableCellStyle": {
                              "rowSpan": 1,
                              "columnSpan": 1,
                              "backgroundColor": {},
                              "paddingLeft": {
                                "magnitude": 5,
                                "unit": "PT"
                              },
                              "paddingRight": {
                                "magnitude": 5,
                                "unit": "PT"
                              },
                              "paddingTop": {
                                "magnitude": 5,
                                "unit": "PT"
                              },
                              "paddingBottom": {
                                "magnitude": 5,
                                "unit": "PT"
                              },
                              "contentAlignment": "TOP"
                            }
                          }
                        ],
                        "tableRowStyle": {
                          "minRowHeight": {
                            "unit": "PT"
                          }
                        }
                      }
                    ],
                    "tableStyle": {
                      "tableColumnProperties": [
                        {
                          "widthType": "EVENLY_DISTRIBUTED"
                        }
                      ]
                    }
                  }
                },
                {
                  "startIndex": 70,
                  "endIndex": 71,
                  "paragraph": {
                    "elements": [
                      {
                        "startIndex": 70,
                        "endIndex": 71,
                        "textRun": {
                          "content": "\n",
                          "textStyle": {}
                        }
                      }
                    ],
                    "paragraphStyle": {
                      "namedStyleType": "NORMAL_TEXT",
                      "alignment": "START",
                      "lineSpacing": 100,
                      "direction": "LEFT_TO_RIGHT",
                      "spacingMode": "COLLAPSE_LISTS",
                      "spaceAbove": {
                        "unit": "PT"
                      },
                      "spaceBelow": {
                        "unit": "PT"
                      },
                      "borderBetween": {
                        "color": {},
                        "width": {
                          "unit": "PT"
                        },
                        "padding": {
                          "unit": "PT"
                        },
                        "dashStyle": "SOLID"
                      },
                      "borderTop": {
                        "color": {},
                        "width": {
                          "unit": "PT"
                        },
                        "padding": {
                          "unit": "PT"
                        },
                        "dashStyle": "SOLID"
                      },
                      "borderBottom": {
                        "color": {},
                        "width": {
                          "unit": "PT"
                        },
                        "padding": {
                          "unit": "PT"
                        },
                        "dashStyle": "SOLID"
                      },
                      "borderLeft": {
                        "color": {},
                        "width": {
                          "unit": "PT"
                        },
                        "padding": {
                          "unit": "PT"
                        },
                        "dashStyle": "SOLID"
                      },
                      "borderRight": {
                        "color": {},
                        "width": {
                          "unit": "PT"
                        },
                        "padding": {
                          "unit": "PT"
                        },
                        "dashStyle": "SOLID"
                      },
                      "indentFirstLine": {
                        "unit": "PT"
                      },
                      "indentStart": {
                        "unit": "PT"
                      },
                      "indentEnd": {
                        "unit": "PT"
                      },
                      "keepLinesTogether": false,
                      "keepWithNext": false,
                      "avoidWidowAndOrphan": false,
                      "shading": {
                        "backgroundColor": {}
                      }
                    }
                  }
                }
              ],
              "tableCellStyle": {
                "rowSpan": 1,
                "columnSpan": 1,
                "backgroundColor": {},
                "paddingLeft": {
                  "magnitude": 5,
                  "unit": "PT"
                },
                "paddingRight": {
                  "magnitude": 5,
                  "unit": "PT"
                },
                "paddingTop": {
                  "magnitude": 5,
                  "unit": "PT"
                },
                "paddingBottom": {
                  "magnitude": 5,
                  "unit": "PT"
                },
                "contentAlignment": "TOP"
              }
            }
          ],
          "tableRowStyle": {
            "minRowHeight": {
              "unit": "PT"
            }
          }
        },
        {
          "startIndex": 71,
          "endIndex": 76,
          "tableCells": [
            {
              "startIndex": 72,
              "endIndex": 74,
              "content": [
                {
                  "startIndex": 73,
                  "endIndex": 74,
                  "paragraph": {
                    "elements": [
                      {
                        "startIndex": 73,
                        "endIndex": 74,
                        "textRun": {
                          "content": "\n",
                          "textStyle": {}
                        }
                      }
                    ],
                    "paragraphStyle": {
                      "namedStyleType": "NORMAL_TEXT",
                      "alignment": "START",
                      "lineSpacing": 100,
                      "direction": "LEFT_TO_RIGHT",
                      "spacingMode": "COLLAPSE_LISTS",
                      "spaceAbove": {
                        "unit": "PT"
                      },
                      "spaceBelow": {
                        "unit": "PT"
                      },
                      "borderBetween": {
                        "color": {},
                        "width": {
                          "unit": "PT"
                        },
                        "padding": {
                          "unit": "PT"
                        },
                        "dashStyle": "SOLID"
                      },
                      "borderTop": {
                        "color": {},
                        "width": {
                          "unit": "PT"
                        },
                        "padding": {
                          "unit": "PT"
                        },
                        "dashStyle": "SOLID"
                      },
                      "borderBottom": {
                        "color": {},
                        "width": {
                          "unit": "PT"
                        },
                        "padding": {
                          "unit": "PT"
                        },
                        "dashStyle": "SOLID"
                      },
                      "borderLeft": {
                        "color": {},
                        "width": {
                          "unit": "PT"
                        },
                        "padding": {
                          "unit": "PT"
                        },
                        "dashStyle": "SOLID"
                      },
                      "borderRight": {
                        "color": {},
                        "width": {
                          "unit": "PT"
                        },
                        "padding": {
                          "unit": "PT"
                        },
                        "dashStyle": "SOLID"
                      },
                      "indentFirstLine": {
                        "unit": "PT"
                      },
                      "indentStart": {
                        "unit": "PT"
                      },
                      "indentEnd": {
                        "unit": "PT"
                      },
                      "keepLinesTogether": false,
                      "keepWithNext": false,
                      "avoidWidowAndOrphan": false,
                      "shading": {
                        "backgroundColor": {}
                      }
                    }
                  }
                }
              ],
              "tableCellStyle": {
                "rowSpan": 1,
                "columnSpan": 1,
                "backgroundColor": {},
                "paddingLeft": {
                  "magnitude": 5,
                  "unit": "PT"
                },
                "paddingRight": {
                  "magnitude": 5,
                  "unit": "PT"
                },
                "paddingTop": {
                  "magnitude": 5,
                  "unit": "PT"
                },
                "paddingBottom": {
                  "magnitude": 5,
                  "unit": "PT"
                },
                "contentAlignment": "TOP"
              }
            },
            {
              "startIndex": 74,
              "endIndex": 76,
              "content": [
                {
                  "startIndex": 75,
                  "endIndex": 76,
                  "paragraph": {
                    "elements": [
                      {
                        "startIndex": 75,
                        "endIndex": 76,
                        "textRun": {
                          "content": "\n",
                          "textStyle": {}
                        }
                      }
                    ],
                    "paragraphStyle": {
                      "namedStyleType": "NORMAL_TEXT",
                      "alignment": "START",
                      "lineSpacing": 100,
                      "direction": "LEFT_TO_RIGHT",
                      "spacingMode": "COLLAPSE_LISTS",
                      "spaceAbove": {
                        "unit": "PT"
                      },
                      "spaceBelow": {
                        "unit": "PT"
                      },
                      "borderBetween": {
                        "color": {},
                        "width": {
                          "unit": "PT"
                        },
                        "padding": {
                          "unit": "PT"
                        },
                        "dashStyle": "SOLID"
                      },
                      "borderTop": {
                        "color": {},
                        "width": {
                          "unit": "PT"
                        },
                        "padding": {
                          "unit": "PT"
                        },
                        "dashStyle": "SOLID"
                      },
                      "borderBottom": {
                        "color": {},
                        "width": {
                          "unit": "PT"
                        },
                        "padding": {
                          "unit": "PT"
                        },
                        "dashStyle": "SOLID"
                      },
                      "borderLeft": {
                        "color": {},
                        "width": {
                          "unit": "PT"
                        },
                        "padding": {
                          "unit": "PT"
                        },
                        "dashStyle": "SOLID"
                      },
                      "borderRight": {
                        "color": {},
                        "width": {
                          "unit": "PT"
                        },
                        "padding": {
                          "unit": "PT"
                        },
                        "dashStyle": "SOLID"
                      },
                      "indentFirstLine": {
                        "unit": "PT"
                      },
                      "indentStart": {
                        "unit": "PT"
                      },
                      "indentEnd": {
                        "unit": "PT"
                      },
                      "keepLinesTogether": false,
                      "keepWithNext": false,
                      "avoidWidowAndOrphan": false,
                      "shading": {
                        "backgroundColor": {}
                      }
                    }
                  }
                }
              ],
              "tableCellStyle": {
                "rowSpan": 1,
                "columnSpan": 1,
                "backgroundColor": {},
                "paddingLeft": {
                  "magnitude": 5,
                  "unit": "PT"
                },
                "paddingRight": {
                  "magnitude": 5,
                  "unit": "PT"
                },
                "paddingTop": {
                  "magnitude": 5,
                  "unit": "PT"
                },
                "paddingBottom": {
                  "magnitude": 5,
                  "unit": "PT"
                },
                "contentAlignment": "TOP"
              }
            }
          ],
          "tableRowStyle": {
            "minRowHeight": {
              "unit": "PT"
            }
          }
        }
      ],
      "tableStyle": {
        "tableColumnProperties": [
          {
            "widthType": "EVENLY_DISTRIBUTED"
          },
          {
            "widthType": "EVENLY_DISTRIBUTED"
          }
        ]
      }
    }
  },
  {
    "startIndex": 77,
    "endIndex": 83,
    "paragraph": {
      "elements": [
        {
          "startIndex": 77,
          "endIndex": 83,
          "textRun": {
            "content": "after\n",
            "textStyle": {}
          }
        }
      ],
      "paragraphStyle": {
        "namedStyleType": "NORMAL_TEXT",
        "direction": "LEFT_TO_RIGHT"
      }
    }
  },
  {
    "startIndex": 83,
    "endIndex": 84,
    "paragraph": {
      "elements": [
        {
          "startIndex": 83,
          "endIndex": 84,
          "textRun": {
            "content": "\n",
            "textStyle": {}
          }
        }
      ],
      "paragraphStyle": {
        "namedStyleType": "NORMAL_TEXT",
        "direction": "LEFT_TO_RIGHT"
      }
    }
  },
  {
    "startIndex": 84,
    "endIndex": 85,
    "paragraph": {
      "elements": [
        {
          "startIndex": 84,
          "endIndex": 85,
          "textRun": {
            "content": "\n",
            "textStyle": {}
          }
        }
      ],
      "paragraphStyle": {
        "namedStyleType": "NORMAL_TEXT",
        "direction": "LEFT_TO_RIGHT"
      }
    }
  },
  {
    "startIndex": 85,
    "endIndex": 109,
    "table": {
      "rows": 1,
      "columns": 1,
      "tableRows": [
        {
          "startIndex": 86,
          "endIndex": 108,
          "tableCells": [
            {
              "startIndex": 87,
              "endIndex": 108,
              "content": [
                {
                  "startIndex": 88,
                  "endIndex": 108,
                  "paragraph": {
                    "elements": [
                      {
                        "startIndex": 88,
                        "endIndex": 108,
                        "textRun": {
                          "content": "Single-cell tablety\n",
                          "textStyle": {}
                        }
                      }
                    ],
                    "paragraphStyle": {
                      "namedStyleType": "NORMAL_TEXT",
                      "alignment": "START",
                      "lineSpacing": 100,
                      "direction": "LEFT_TO_RIGHT",
                      "spacingMode": "COLLAPSE_LISTS",
                      "spaceAbove": {
                        "unit": "PT"
                      },
                      "spaceBelow": {
                        "unit": "PT"
                      },
                      "borderBetween": {
                        "color": {},
                        "width": {
                          "unit": "PT"
                        },
                        "padding": {
                          "unit": "PT"
                        },
                        "dashStyle": "SOLID"
                      },
                      "borderTop": {
                        "color": {},
                        "width": {
                          "unit": "PT"
                        },
                        "padding": {
                          "unit": "PT"
                        },
                        "dashStyle": "SOLID"
                      },
                      "borderBottom": {
                        "color": {},
                        "width": {
                          "unit": "PT"
                        },
                        "padding": {
                          "unit": "PT"
                        },
                        "dashStyle": "SOLID"
                      },
                      "borderLeft": {
                        "color": {},
                        "width": {
                          "unit": "PT"
                        },
                        "padding": {
                          "unit": "PT"
                        },
                        "dashStyle": "SOLID"
                      },
                      "borderRight": {
                        "color": {},
                        "width": {
                          "unit": "PT"
                        },
                        "padding": {
                          "unit": "PT"
                        },
                        "dashStyle": "SOLID"
                      },
                      "indentFirstLine": {
                        "unit": "PT"
                      },
                      "indentStart": {
                        "unit": "PT"
                      },
                      "indentEnd": {
                        "unit": "PT"
                      },
                      "keepLinesTogether": false,
                      "keepWithNext": false,
                      "avoidWidowAndOrphan": false,
                      "shading": {
                        "backgroundColor": {}
                      }
                    }
                  }
                }
              ],
              "tableCellStyle": {
                "rowSpan": 1,
                "columnSpan": 1,
                "backgroundColor": {},
                "paddingLeft": {
                  "magnitude": 5,
                  "unit": "PT"
                },
                "paddingRight": {
                  "magnitude": 5,
                  "unit": "PT"
                },
                "paddingTop": {
                  "magnitude": 5,
                  "unit": "PT"
                },
                "paddingBottom": {
                  "magnitude": 5,
                  "unit": "PT"
                },
                "contentAlignment": "TOP"
              }
            }
          ],
          "tableRowStyle": {
            "minRowHeight": {
              "magnitude": 19.39892578125,
              "unit": "PT"
            }
          }
        }
      ],
      "tableStyle": {
        "tableColumnProperties": [
          {
            "widthType": "EVENLY_DISTRIBUTED"
          }
        ]
      }
    }
  },
  {
    "startIndex": 109,
    "endIndex": 110,
    "paragraph": {
      "elements": [
        {
          "startIndex": 109,
          "endIndex": 110,
          "textRun": {
            "content": "\n",
            "textStyle": {}
          }
        }
      ],
      "paragraphStyle": {
        "namedStyleType": "NORMAL_TEXT",
        "direction": "LEFT_TO_RIGHT"
      }
    }
  },
  {
    "startIndex": 110,
    "endIndex": 111,
    "paragraph": {
      "elements": [
        {
          "startIndex": 110,
          "endIndex": 111,
          "textRun": {
            "content": "\n",
            "textStyle": {}
          }
        }
      ],
      "paragraphStyle": {
        "namedStyleType": "NORMAL_TEXT",
        "direction": "LEFT_TO_RIGHT"
      }
    }
  },
  {
    "startIndex": 111,
    "endIndex": 217,
    "paragraph": {
      "elements": [
        {
          "startIndex": 111,
          "endIndex": 217,
          "textRun": {
            "content": "asdfasdfasdfasdfasdf sad fasdf asdf asdf asdf asdf asdfasdf asdf asdf asdf asdf asdf sadf asdf asdf asdf \n",
            "textStyle": {
              "bold": true
            }
          }
        }
      ],
      "paragraphStyle": {
        "namedStyleType": "NORMAL_TEXT",
        "direction": "LEFT_TO_RIGHT"
      }
    }
  }
]